flair_api/__init__.py
flair_api/client.py
flair_client-1.0.0.dist-info/DESCRIPTION.rst
flair_client-1.0.0.dist-info/METADATA
flair_client-1.0.0.dist-info/RECORD
flair_client-1.0.0.dist-info/WHEEL
flair_client-1.0.0.dist-info/metadata.json
flair_client-1.0.0.dist-info/top_level.txt
